JohnServerAPI/JohnServerAPI.py
JohnServerAPI/__init__.py
test_johnserverapi/__init__.py
test_johnserverapi/test_johnserverapi.py
JohnServerAPI-0.0.2.dist-info/METADATA
JohnServerAPI-0.0.2.dist-info/WHEEL
JohnServerAPI-0.0.2.dist-info/top_level.txt
JohnServerAPI-0.0.2.dist-info/RECORD
