Metadata-Version: 2.1
Name: JohnServerAPI
Version: 0.0.2
Summary: This is a module to interact with Server and Client
Author: John
Author-email: myemail@example.com
Requires-Dist: requests
Requires-Dist: numpy
Requires-Dist: matplotlib
Requires-Dist: ipaddress
